setup.py
IntroductionToPresentation/__init__.py
WorkingWithCharts/__init__.py
WorkingWithPresentation/__init__.py
WorkingWithShapes/__init__.py
WorkingWithSlidesInPresentation/__init__.py
WorkingWithSmartArt/__init__.py
WorkingWithTables/__init__.py
WorkingWithText/__init__.py
aspose_slides_java_for_python.egg-info/PKG-INFO
aspose_slides_java_for_python.egg-info/SOURCES.txt
aspose_slides_java_for_python.egg-info/dependency_links.txt
aspose_slides_java_for_python.egg-info/top_level.txt