Metadata-Version: 1.1
Name: aspose-slides-java-for-python
Version: 1.0
Summary: Aspose.Slides Java for Python is a project that demonstrates / provides the Aspose.Slides for Java API usage examples in Python.
Home-page: http://www.aspose.com/docs/display/slidesjava/Aspose.Slides+Java+for+Python
Author: Fahad Adeel
Author-email: slides@aspose.com
License: UNKNOWN
Platform: UNKNOWN
Classifier: Programming Language :: Python
Classifier: Programming Language :: Python :: 2
Classifier: License :: OSI Approved :: MIT License
Classifier: Operating System :: OS Independent
